LICENSE
MANIFEST.in
setup.cfg
setup.py
virtstrap/__init__.py
virtstrap/argparse.py
virtstrap/basecommand.py
virtstrap/config.py
virtstrap/constants.py
virtstrap/exceptions.py
virtstrap/hooks.py
virtstrap/joined.py
virtstrap/loaders.py
virtstrap/locker.py
virtstrap/log.py
virtstrap/options.py
virtstrap/project.py
virtstrap/registry.py
virtstrap/requirements.py
virtstrap/runner.py
virtstrap/tempfiler.py
virtstrap/templating.py
virtstrap/utils.py
virtstrap/commands/__init__.py
virtstrap/commands/clean.py
virtstrap/commands/info.py
virtstrap/packages/__init__.py
virtstrap/packages/simpleyaml/__init__.py
virtstrap/packages/simpleyaml/composer.py
virtstrap/packages/simpleyaml/constructor.py
virtstrap/packages/simpleyaml/dumper.py
virtstrap/packages/simpleyaml/emitter.py
virtstrap/packages/simpleyaml/error.py
virtstrap/packages/simpleyaml/events.py
virtstrap/packages/simpleyaml/loader.py
virtstrap/packages/simpleyaml/nodes.py
virtstrap/packages/simpleyaml/parser.py
virtstrap/packages/simpleyaml/reader.py
virtstrap/packages/simpleyaml/representer.py
virtstrap/packages/simpleyaml/resolver.py
virtstrap/packages/simpleyaml/scanner.py
virtstrap/packages/simpleyaml/serializer.py
virtstrap/packages/simpleyaml/tokens.py
virtstrap/packages/tempita/__init__.py
virtstrap/packages/tempita/_looper.py
virtstrap/packages/tempita/compat3.py
virtstrap/templates/init/activate.sh.tmpl
virtstrap/templates/init/quickactivate.sh.tmpl
virtstrap/testing/__init__.py
virtstrap/testing/context.py
virtstrap/testing/data.py
virtstrap/testing/directory.py
virtstrap/testing/fakes.py
virtstrap/testing/pypi.py
virtstrap/testing/shunt.py
virtstrap/testing/subproc.py
virtstrap_core.egg-info/PKG-INFO
virtstrap_core.egg-info/SOURCES.txt
virtstrap_core.egg-info/dependency_links.txt
virtstrap_core.egg-info/entry_points.txt
virtstrap_core.egg-info/not-zip-safe
virtstrap_core.egg-info/top_level.txt