Metadata-Version: 1.1
Name: virtstrap-core
Version: 0.3.10
Summary: A bootstrapping mechanism for virtualenv+pip and shell scripts
Home-page: https://github.com/ravenac95/virtstrap-core
Author: Reuven V. Gonzales
Author-email: reuven@tobetter.us
License: MIT
Platform: *nix
Classifier: License :: OSI Approved :: MIT License
Classifier: Intended Audience :: Developers
Classifier: Programming Language :: Python
Classifier: Operating System :: POSIX
Classifier: Topic :: Software Development :: Build Tools
